rhodes/__init__.py
rhodes/_converters.py
rhodes/_runtime_types.py
rhodes/_serialization.py
rhodes/_types.py
rhodes/_util.py
rhodes/_validators.py
rhodes/choice_rules.py
rhodes/choice_rules.pyi
rhodes/exceptions.py
rhodes/identifiers.py
rhodes/py.typed
rhodes/structures.py
rhodes/structures.pyi
rhodes/states/__init__.py
rhodes/states/__init__.pyi
rhodes/states/_parameters.py
rhodes/states/services/__init__.py
rhodes/states/services/_util.py
rhodes/states/services/awslambda.py
rhodes/states/services/awslambda.pyi
rhodes/states/services/batch.py
rhodes/states/services/batch.pyi
rhodes/states/services/dynamodb.py
rhodes/states/services/dynamodb.pyi
rhodes/states/services/ecs.py
rhodes/states/services/ecs.pyi
rhodes/states/services/glue.py
rhodes/states/services/glue.pyi
rhodes/states/services/sagemaker.py
rhodes/states/services/sagemaker.pyi
rhodes/states/services/sns.py
rhodes/states/services/sns.pyi
rhodes/states/services/sqs.py
rhodes/states/services/sqs.pyi
rhodes/states/services/stepfunctions.py
rhodes/states/services/stepfunctions.pyi
rhodes-0.5.4.data/data/CHANGELOG.rst
rhodes-0.5.4.data/data/LICENSE
rhodes-0.5.4.data/data/README.rst
rhodes-0.5.4.data/data/requirements.txt
rhodes-0.5.4.dist-info/LICENSE
rhodes-0.5.4.dist-info/METADATA
rhodes-0.5.4.dist-info/WHEEL
rhodes-0.5.4.dist-info/top_level.txt
rhodes-0.5.4.dist-info/RECORD
