Metadata-Version: 2.1
Name: rhodes
Version: 0.5.4
Summary: rhodes
Home-page: https://github.com/mattsb42/rhodes
Author: Matt Bullock
Author-email: m@ttsb42.com
Maintainer: Matt Bullock
License: Apache 2.0
Keywords: rhodes rhodes
Platform: UNKNOWN
Classifier: Development Status :: 3 - Alpha
Classifier: Intended Audience :: Developers
Classifier: Natural Language :: English
Classifier: License :: OSI Approved :: Apache Software License
Classifier: Programming Language :: Python
Classifier: Programming Language :: Python :: 3
Classifier: Programming Language :: Python :: 3.6
Classifier: Programming Language :: Python :: 3.7
Classifier: Programming Language :: Python :: Implementation :: CPython
Requires-Python: >=3.6
Requires-Dist: attrs
Requires-Dist: pytz
Requires-Dist: jsonpath-rw
Requires-Dist: troposphere
